{
    "route": "27A",
    "region": "NT",
    "gtfsId": "2007861",
    "bound": {
        "O": {
            "timetable": [
                {
                    "weekday": "12345",
                    "weekday_zh": "\u661f\u671f\u4e00\u81f3\u4e94",
                    "weekday_en": "Monday to Friday",
                    "times": [
                        {
                            "period": "06:40-08:00",
                            "frequency": "20"
                        },
                        {
                            "period": "08:00-09:30",
                            "frequency": "15"
                        },
                        {
                            "period": "09:30-10:00",
                            "frequency": "20"
                        },
                        {
                            "period": "17:00-18:00",
                            "frequency": "12"
                        },
                        {
                            "period": "18:00-19:00",
                            "frequency": "15"
                        }
                    ]
                },
                {
                    "weekday": "67",
                    "weekday_zh": "\u661f\u671f\u516d\u3001\u65e5\u53ca\u516c\u773e\u5047\u671f",
                    "weekday_en": "Saturday, Sunday & Public Holidays",
                    "times": [
                        {
                            "period": "06:40-08:00",
                            "frequency": "20"
                        },
                        {
                            "period": "08:00-09:30",
                            "frequency": "15"
                        },
                        {
                            "period": "09:30-10:00",
                            "frequency": "20"
                        },
                        {
                            "period": "17:00-19:00",
                            "frequency": "15"
                        }
                    ]
                }
            ]
        },
        "I": {
            "timetable": [
                {
                    "weekday": "12345",
                    "weekday_zh": "\u661f\u671f\u4e00\u81f3\u4e94",
                    "weekday_en": "Monday to Friday",
                    "times": [
                        {
                            "period": "06:20-08:00",
                            "frequency": "20"
                        },
                        {
                            "period": "08:00-09:30",
                            "frequency": "15"
                        },
                        {
                            "period": "09:30-10:00",
                            "frequency": "20"
                        },
                        {
                            "period": "17:00-18:00",
                            "frequency": "12"
                        },
                        {
                            "period": "18:00-19:00",
                            "frequency": "15"
                        }
                    ]
                },
                {
                    "weekday": "67",
                    "weekday_zh": "\u661f\u671f\u516d\u3001\u65e5\u53ca\u516c\u773e\u5047\u671f",
                    "weekday_en": "Saturday, Sunday & Public Holidays",
                    "times": [
                        {
                            "period": "06:20-08:00",
                            "frequency": "20"
                        },
                        {
                            "period": "08:00-09:30",
                            "frequency": "15"
                        },
                        {
                            "period": "09:30-10:00",
                            "frequency": "20"
                        },
                        {
                            "period": "17:00-19:00",
                            "frequency": "15"
                        }
                    ]
                }
            ]
        }
    }
}