{
    "route": "74",
    "region": "NT",
    "gtfsId": "2008554",
    "bound": {
        "O": {
            "timetable": [
                {
                    "weekday": "1234567",
                    "weekday_zh": "\u6bcf\u5929",
                    "weekday_en": "Daily",
                    "times": [
                        {
                            "period": "05:45-06:30",
                            "frequency": "15"
                        },
                        {
                            "period": "06:30-13:00",
                            "frequency": "8"
                        },
                        {
                            "period": "13:00-22:00",
                            "frequency": "10"
                        }
                    ]
                }
            ]
        },
        "I": {
            "timetable": [
                {
                    "weekday": "1234567",
                    "weekday_zh": "\u6bcf\u5929",
                    "weekday_en": "Daily",
                    "times": [
                        {
                            "period": "06:00-06:45",
                            "frequency": "15"
                        },
                        {
                            "period": "06:45-13:20",
                            "frequency": "8"
                        },
                        {
                            "period": "13:20-21:30",
                            "frequency": "10"
                        },
                        {
                            "period": "21:30-21:45",
                            "frequency": "15"
                        }
                    ]
                }
            ]
        }
    }
}