{
    "route": "48",
    "region": "KLN",
    "gtfsId": "2007332",
    "bound": {
        "O": {
            "timetable": [
                {
                    "weekday": "1234567",
                    "weekday_zh": "\u6bcf\u5929",
                    "weekday_en": "Daily",
                    "times": [
                        {
                            "period": "22:45-23:45",
                            "frequency": "8"
                        }
                    ]
                }
            ]
        }
    }
}